paperops/config.py
paperops-0.1.5.dist-info/METADATA
paperops-0.1.5.dist-info/WHEEL
paperops-0.1.5.dist-info/licenses/LICENSE
paperops-0.1.5.dist-info/RECORD
